Metadata-Version: 2.1
Name: python-logstash-tradingstrategy
Version: 0.5.0
Summary: Python logging handler for Logstash (forked).
Home-page: https://github.com/tradingstrategy-ai/python-logstash/
Author: Mikko Ohtamaa
Author-email: mikko@capitalgram.com
License: MIT
Classifier: Development Status :: 4 - Beta
Classifier: Intended Audience :: Developers
Classifier: License :: OSI Approved :: MIT License
Classifier: Operating System :: OS Independent
Classifier: Programming Language :: Python
Classifier: Programming Language :: Python :: 2
Classifier: Programming Language :: Python :: 3
Classifier: Topic :: Internet :: WWW/HTTP
Classifier: Topic :: Software Development :: Libraries :: Python Modules
Classifier: Topic :: System :: Logging
License-File: LICENSE
